{
    "/js/app.js": "/js/app.js",
    "/css/app.css": "/css/app.css",
    "/0.52d8a9e26397dc8458c7.hot-update.js": "/0.52d8a9e26397dc8458c7.hot-update.js",
    "/0.b19b22f8dd61fa46a343.hot-update.js": "/0.b19b22f8dd61fa46a343.hot-update.js",
    "/0.f5e1cbe8e9c2907ac0fe.hot-update.js": "/0.f5e1cbe8e9c2907ac0fe.hot-update.js",
    "/0.94ec39c6283a7be76514.hot-update.js": "/0.94ec39c6283a7be76514.hot-update.js",
    "/0.c6294bf864197a98a098.hot-update.js": "/0.c6294bf864197a98a098.hot-update.js",
    "/0.393e6887350942ec28b9.hot-update.js": "/0.393e6887350942ec28b9.hot-update.js",
    "/0.f5d52a0cb0cda172e1b5.hot-update.js": "/0.f5d52a0cb0cda172e1b5.hot-update.js",
    "/0.6750e933fe7e223bf237.hot-update.js": "/0.6750e933fe7e223bf237.hot-update.js",
    "/0.ce000953e51a3089bbdc.hot-update.js": "/0.ce000953e51a3089bbdc.hot-update.js",
    "/0.3ab639c88fc4efbf9626.hot-update.js": "/0.3ab639c88fc4efbf9626.hot-update.js",
    "/0.2b61e6ee8f4d6cc18b28.hot-update.js": "/0.2b61e6ee8f4d6cc18b28.hot-update.js",
    "/0.d9f76ffcd96964daa786.hot-update.js": "/0.d9f76ffcd96964daa786.hot-update.js",
    "/0.a6d6a5c0c914ba534c41.hot-update.js": "/0.a6d6a5c0c914ba534c41.hot-update.js",
    "/0.9131e1d06711ce9bb700.hot-update.js": "/0.9131e1d06711ce9bb700.hot-update.js",
    "/0.e207889c5a9db62e78d2.hot-update.js": "/0.e207889c5a9db62e78d2.hot-update.js",
    "/0.4dcced121567e77b932e.hot-update.js": "/0.4dcced121567e77b932e.hot-update.js",
    "/0.dd9c5c51b929e05662a5.hot-update.js": "/0.dd9c5c51b929e05662a5.hot-update.js",
    "/0.e5d20a5c4b38b3f3bc99.hot-update.js": "/0.e5d20a5c4b38b3f3bc99.hot-update.js",
    "/0.5eb5d198ad1727125afe.hot-update.js": "/0.5eb5d198ad1727125afe.hot-update.js",
    "/0.a796acf4fed68027c517.hot-update.js": "/0.a796acf4fed68027c517.hot-update.js",
    "/0.c67bcc257a9da61fc3e0.hot-update.js": "/0.c67bcc257a9da61fc3e0.hot-update.js",
    "/0.63a064f9cc2c9b4c82c2.hot-update.js": "/0.63a064f9cc2c9b4c82c2.hot-update.js",
    "/0.bbd15911cf55cf2296fa.hot-update.js": "/0.bbd15911cf55cf2296fa.hot-update.js",
    "/0.e24a7b370e49c703049f.hot-update.js": "/0.e24a7b370e49c703049f.hot-update.js",
    "/0.1bf88ebad326c5b41e62.hot-update.js": "/0.1bf88ebad326c5b41e62.hot-update.js"
}